{
  "tasks": [
    {
      "id": 1,
      "description": "Doctors Appointment",
      "day": "March 1st at 2:30pm",
      "reminder": true
    },
    {
      "id": 2,
      "description": "Meeting at School",
      "day": "March 3rd at 1:30pm",
      "reminder": false
    },
    {
      "description": "adfsdfasdf",
      "day": "sadfasdfasd",
      "reminder": false,
      "id": 7
    },
    {
      "description": "werweweqrqwerew",
      "day": "ewqrqwerwerrew",
      "reminder": false,
      "id": 8
    },
    {
      "description": "adsfsdfas asdfasdfsadfasl;kfj;alskfj ;aklsdfj;alskfd;laksjd;f alksdfj",
      "day": "dlskjf",
      "reminder": false,
      "id": 9
    }
  ]
}